benchmarks/__init__.py
benchmarks/benchmark_layer.py
benchmarks/check_threshold.py
benchmarks/generate_report.py
benchmarks/layers.py
benchmarks/run_benchmarks.py
benchmarks/utils.py
examples/__init__.py
examples/char-lstm-classification.py
examples/cifar10.py
examples/dcgan.py
examples/imdb.py
examples/mnist.py
examples/mnist_lightning.py
examples/vision_benchmark.py
opacus/__init__.py
opacus/data_loader.py
opacus/distributed.py
opacus/lightning.py
opacus/privacy_engine.py
opacus/version.py
opacus/accountants/__init__.py
opacus/accountants/accountant.py
opacus/accountants/gdp.py
opacus/accountants/prv.py
opacus/accountants/rdp.py
opacus/accountants/utils.py
opacus/accountants/analysis/__init__.py
opacus/accountants/analysis/gdp.py
opacus/accountants/analysis/rdp.py
opacus/accountants/analysis/prv/__init__.py
opacus/accountants/analysis/prv/compose.py
opacus/accountants/analysis/prv/domain.py
opacus/accountants/analysis/prv/prvs.py
opacus/grad_sample/__init__.py
opacus/grad_sample/conv.py
opacus/grad_sample/dp_multihead_attention.py
opacus/grad_sample/dp_rnn.py
opacus/grad_sample/embedding.py
opacus/grad_sample/embedding_norm_sample.py
opacus/grad_sample/functorch.py
opacus/grad_sample/grad_sample_module.py
opacus/grad_sample/grad_sample_module_fast_gradient_clipping.py
opacus/grad_sample/group_norm.py
opacus/grad_sample/gsm_base.py
opacus/grad_sample/gsm_exp_weights.py
opacus/grad_sample/gsm_no_op.py
opacus/grad_sample/instance_norm.py
opacus/grad_sample/layer_norm.py
opacus/grad_sample/linear.py
opacus/grad_sample/rms_norm.py
opacus/grad_sample/utils.py
opacus/layers/__init__.py
opacus/layers/dp_multihead_attention.py
opacus/layers/dp_rnn.py
opacus/layers/param_rename.py
opacus/optimizers/__init__.py
opacus/optimizers/adaclipoptimizer.py
opacus/optimizers/ddp_perlayeroptimizer.py
opacus/optimizers/ddpoptimizer.py
opacus/optimizers/ddpoptimizer_fast_gradient_clipping.py
opacus/optimizers/optimizer.py
opacus/optimizers/optimizer_fast_gradient_clipping.py
opacus-1.5.4.dist-info/licenses/LICENSE
opacus-1.5.4.dist-info/METADATA
opacus-1.5.4.dist-info/WHEEL
opacus-1.5.4.dist-info/top_level.txt
opacus-1.5.4.dist-info/RECORD
